CHANGELOG.rst
LICENSE.txt
MANIFEST.in
README.rst
TODO.txt
VERSION.txt
setup.cfg
setup.py
pxml/__init__.py
pxml/test.py
pxml.egg-info/PKG-INFO
pxml.egg-info/SOURCES.txt
pxml.egg-info/dependency_links.txt
pxml.egg-info/entry_points.txt
pxml.egg-info/requires.txt
pxml.egg-info/top_level.txt
pxml.egg-info/zip-safe