Metadata-Version: 1.1
Name: pxml
Version: 0.2.10
Summary: A python library and command-line tool to "prettify" and colorize XML.
Home-page: http://github.com/metagriffin/pxml
Author: metagriffin
Author-email: mg.pypi@uberdev.org
License: GPLv3+
Keywords: pretty xml command-line library
Platform: any
Classifier: Development Status :: 5 - Production/Stable
Classifier: Environment :: Console
Classifier: Intended Audience :: Developers
Classifier: Intended Audience :: System Administrators
Classifier: Natural Language :: English
Classifier: Operating System :: OS Independent
Classifier: Programming Language :: Python
Classifier: Topic :: Software Development
Classifier: Topic :: Software Development :: Libraries :: Python Modules
Classifier: Topic :: Utilities
Classifier: License :: OSI Approved :: GNU General Public License v3 or later (GPLv3+)
